integration_tests/__init__.py
integration_tests/base.py
integration_tests/test_stir.py
tests/__init__.py
tests/test_conf.py
tests/test_handlers.py
tests/test_helpers.py
tests/test_renderer.py
tests/test_runner.py
tests/test_settings.py
testtube/__init__.py
testtube/conf.py
testtube/core.py
testtube/handlers.py
testtube/helpers.py
testtube/renderer.py
testtube/runner.py
testtube-1.1.0.data/scripts/stir
testtube-1.1.0.dist-info/DESCRIPTION.rst
testtube-1.1.0.dist-info/METADATA
testtube-1.1.0.dist-info/RECORD
testtube-1.1.0.dist-info/WHEEL
testtube-1.1.0.dist-info/metadata.json
testtube-1.1.0.dist-info/top_level.txt
