Metadata-Version: 2.0
Name: testtube
Version: 1.1.0
Summary: 
Requires-Dist: six (>=1.2.0)
Requires-Dist: termcolor (==1.1.0)
Requires-Dist: watchdog (==0.8.3)
